CHANGELOG.txt
LICENSE.txt
MANIFEST.in
README.txt
setup.py
LibForShiva/__init__.py
LibForShiva/calculs.py
LibForShiva/markups.py
LibForShiva.egg-info/PKG-INFO
LibForShiva.egg-info/SOURCES.txt
LibForShiva.egg-info/dependency_links.txt
LibForShiva.egg-info/requires.txt
LibForShiva.egg-info/top_level.txt