Metadata-Version: 2.1
Name: LibForShiva
Version: 1.3
Summary: Librairie de simplification pour Shiva.
Home-page: UNKNOWN
Author: Guillaume ROCHE
Author-email: g.roche1712@protonmail.com
License: MIT
Keywords: Shiva
Platform: UNKNOWN
Classifier: Development Status :: 5 - Production/Stable
Classifier: Operating System :: Microsoft :: Windows :: Windows 10
Classifier: License :: OSI Approved :: MIT License
Classifier: Programming Language :: Python :: 3
